setup.py
kronos/__init__.py
kronos/settings.py
kronos/utils.py
kronos.egg-info/PKG-INFO
kronos.egg-info/SOURCES.txt
kronos.egg-info/dependency_links.txt
kronos.egg-info/top_level.txt
kronos/management/__init__.py
kronos/management/commands/__init__.py
kronos/management/commands/installtasks.py
kronos/management/commands/runtask.py
kronos/management/commands/uninstalltasks.py